nonebot_plugin_abot_place-0.1.0.post3.dist-info/METADATA
nonebot_plugin_abot_place-0.1.0.post3.dist-info/WHEEL
nonebot_plugin_abot_place-0.1.0.post3.dist-info/licenses/LICENSE
nonebot_plugin_abot_place/__init__.py
nonebot_plugin_abot_place/color.py
nonebot_plugin_abot_place/config.py
nonebot_plugin_abot_place/database.py
nonebot_plugin_abot_place/draw.py
nonebot_plugin_abot_place/static/sarasa-mono-sc-semibold.ttf
nonebot_plugin_abot_place/utils.py
nonebot_plugin_abot_place-0.1.0.post3.dist-info/RECORD
