Metadata-Version: 2.1
Name: nonebot-plugin-abot-place
Version: 0.1.0.post3
Summary: 移植于 ABot 的画板插件，可以和所有的 bot 用户一起画画！
Author-Email: djkcyl <cyl@cyllive.cn>, Well404 <well_404@outlook.com>
License: MIT
Requires-Python: <4.0,>=3.8
Requires-Dist: nonebot-adapter-onebot>=2.2.2
Requires-Dist: pillow>=9.5.0
Requires-Dist: SQLAlchemy>=2.0.11
Requires-Dist: importlib-metadata>=6.6.0
Requires-Dist: nonebot-plugin-localstore>=0.4.1
Requires-Dist: nonebot2>=2.0.0
